mingk42_cmd/__init__.py
mingk42_cmd/cmd.py
mingk42_cmd-0.1.1.dist-info/METADATA
mingk42_cmd-0.1.1.dist-info/WHEEL
mingk42_cmd-0.1.1.dist-info/entry_points.txt
mingk42_cmd-0.1.1.dist-info/top_level.txt
mingk42_cmd-0.1.1.dist-info/RECORD
