Metadata-Version: 2.1
Name: mingk42_cmd
Version: 0.1.1
Summary: Default template for PDM package
Author-email: Mingk42 <xoals123456t@gmail.com>
License: MIT
Requires-Python: >=3.9
Requires-Dist: mingk42-lotto >=0.2.0
